erad/__init__.py
erad/constants.py
erad/exceptions.py
erad/cypher_queries/load_data_v1.cypher
erad/data/World_Earthquakes_1960_2016.csv
erad/db/__init__.py
erad/db/credential_model.py
erad/db/disaster_input_model.py
erad/db/inject_earthquake.py
erad/db/inject_flooding.py
erad/db/neo4j_.py
erad/db/utils.py
erad/db/assets/__init__.py
erad/db/assets/critical_infras.py
erad/db/assets/distribution_lines.py
erad/metrics/__init__.py
erad/metrics/check_microgrid.py
erad/metrics/metric.py
erad/programs/__init__.py
erad/programs/backup.py
erad/programs/microgrid.py
erad/scenarios/__init__.py
erad/scenarios/abstract_scenario.py
erad/scenarios/common.py
erad/scenarios/earthquake_scenario.py
erad/scenarios/fire_scenario.py
erad/scenarios/flood_scenario.py
erad/scenarios/flows.csv
erad/scenarios/utilities.py
erad/scenarios/wind_scenario.py
erad/utils/__init__.py
erad/utils/ditto_utils.py
erad/utils/hifld_utils.py
erad/utils/opendss_utils.py
erad/utils/overpass.py
erad/utils/util.py
erad/visualization/__init__.py
erad/visualization/plot_graph.py
nrel_erad-1.0.0.dist-info/METADATA
nrel_erad-1.0.0.dist-info/WHEEL
nrel_erad-1.0.0.dist-info/licenses/LICENSE.txt
nrel_erad-1.0.0.dist-info/RECORD
