Metadata-Version: 2.3
Name: NREL-erad
Version: 1.0.0
Summary: Graph based scalable tool for computing equitable resilience metrics for distribution systems.
Project-URL: Homepage, https://github.com/nrel/erad
Author-email: Kapil Duwadi <kapil.duwadi@nrel.gov>, Aadil Latif <aadil.altif@nrel.gov>, Kwami Sedzro <sherinann.abraham@nrel.gov>, Sherin Ann Abraham <kwami.sedzro@nrel.gov>, Bryan Palmintier <bryan.palmintier@nrel.gov>
License-File: LICENSE.txt
Keywords: Distribution,Earthquake,Equity,Fire,Flooding,Power,Python,Resilience,Systems
Classifier: License :: OSI Approved :: BSD License
Classifier: Operating System :: OS Independent
Classifier: Programming Language :: Python :: 3.8
Requires-Python: >=3.8
Requires-Dist: boto3
Requires-Dist: botocore
Requires-Dist: ditto-py
Requires-Dist: geojson
Requires-Dist: geopandas
Requires-Dist: geopy
Requires-Dist: graphdatascience
Requires-Dist: jupyter
Requires-Dist: matplotlib
Requires-Dist: neo4j-driver
Requires-Dist: networkx
Requires-Dist: opendssdirect-py
Requires-Dist: pandas
Requires-Dist: plotly
Requires-Dist: pydantic~=1.10.14
Requires-Dist: pytest
Requires-Dist: python-dotenv
Requires-Dist: pyyaml
Requires-Dist: rasterio
Requires-Dist: requests
Requires-Dist: scipy
Requires-Dist: shapely
Requires-Dist: stateplane
Requires-Dist: xmltodict
Provides-Extra: dev
Requires-Dist: black; extra == 'dev'
Requires-Dist: mkdocs; extra == 'dev'
Requires-Dist: mkdocs-jupyter; extra == 'dev'
Requires-Dist: mkdocs-material; extra == 'dev'
Requires-Dist: mkdocstrings[python]; extra == 'dev'
Requires-Dist: pylint; extra == 'dev'
